{
  "lastUpdated": "2026-05-02T01:48:44.781Z",
  "global": {
    "total_videos": 713,
    "avg_view_counter": 521,
    "median_view_counter": 299,
    "avg_mylist_counter": 20,
    "median_mylist_counter": 15
  },
  "stats": [
    {
      "group": 1,
      "avg_view_counter": 1096,
      "avg_mylist_counter": 32,
      "median_view_counter": 777,
      "median_mylist_counter": 32
    },
    {
      "group": 2,
      "avg_view_counter": 676,
      "avg_mylist_counter": 23,
      "median_view_counter": 647,
      "median_mylist_counter": 23
    },
    {
      "group": 3,
      "avg_view_counter": 807,
      "avg_mylist_counter": 32,
      "median_view_counter": 682,
      "median_mylist_counter": 26
    },
    {
      "group": 4,
      "avg_view_counter": 349,
      "avg_mylist_counter": 17,
      "median_view_counter": 254,
      "median_mylist_counter": 14
    },
    {
      "group": 5,
      "avg_view_counter": 330,
      "avg_mylist_counter": 15,
      "median_view_counter": 298,
      "median_mylist_counter": 12
    },
    {
      "group": 6,
      "avg_view_counter": 534,
      "avg_mylist_counter": 14,
      "median_view_counter": 368,
      "median_mylist_counter": 12
    },
    {
      "group": 7,
      "avg_view_counter": 368,
      "avg_mylist_counter": 18,
      "median_view_counter": 351,
      "median_mylist_counter": 16
    },
    {
      "group": 8,
      "avg_view_counter": 658,
      "avg_mylist_counter": 31,
      "median_view_counter": 387,
      "median_mylist_counter": 17
    },
    {
      "group": 9,
      "avg_view_counter": 407,
      "avg_mylist_counter": 20,
      "median_view_counter": 265,
      "median_mylist_counter": 13
    },
    {
      "group": 10,
      "avg_view_counter": 465,
      "avg_mylist_counter": 16,
      "median_view_counter": 366,
      "median_mylist_counter": 12
    },
    {
      "group": 11,
      "avg_view_counter": 424,
      "avg_mylist_counter": 17,
      "median_view_counter": 332,
      "median_mylist_counter": 16
    },
    {
      "group": 12,
      "avg_view_counter": 508,
      "avg_mylist_counter": 14,
      "median_view_counter": 264,
      "median_mylist_counter": 12
    },
    {
      "group": 13,
      "avg_view_counter": 616,
      "avg_mylist_counter": 15,
      "median_view_counter": 306,
      "median_mylist_counter": 15
    },
    {
      "group": 14,
      "avg_view_counter": 1108,
      "avg_mylist_counter": 41,
      "median_view_counter": 423,
      "median_mylist_counter": 30
    },
    {
      "group": 15,
      "avg_view_counter": 556,
      "avg_mylist_counter": 13,
      "median_view_counter": 252,
      "median_mylist_counter": 12
    },
    {
      "group": 16,
      "avg_view_counter": 512,
      "avg_mylist_counter": 21,
      "median_view_counter": 285,
      "median_mylist_counter": 15
    },
    {
      "group": 17,
      "avg_view_counter": 643,
      "avg_mylist_counter": 24,
      "median_view_counter": 282,
      "median_mylist_counter": 15
    },
    {
      "group": 18,
      "avg_view_counter": 479,
      "avg_mylist_counter": 14,
      "median_view_counter": 261,
      "median_mylist_counter": 13
    },
    {
      "group": 19,
      "avg_view_counter": 352,
      "avg_mylist_counter": 21,
      "median_view_counter": 288,
      "median_mylist_counter": 15
    },
    {
      "group": 20,
      "avg_view_counter": 278,
      "avg_mylist_counter": 17,
      "median_view_counter": 245,
      "median_mylist_counter": 14
    },
    {
      "group": 21,
      "avg_view_counter": 637,
      "avg_mylist_counter": 20,
      "median_view_counter": 398,
      "median_mylist_counter": 12
    },
    {
      "group": 22,
      "avg_view_counter": 663,
      "avg_mylist_counter": 22,
      "median_view_counter": 309,
      "median_mylist_counter": 13
    },
    {
      "group": 23,
      "avg_view_counter": 322,
      "avg_mylist_counter": 19,
      "median_view_counter": 286,
      "median_mylist_counter": 15
    },
    {
      "group": 24,
      "avg_view_counter": 598,
      "avg_mylist_counter": 20,
      "median_view_counter": 267,
      "median_mylist_counter": 17
    },
    {
      "group": 25,
      "avg_view_counter": 323,
      "avg_mylist_counter": 16,
      "median_view_counter": 263,
      "median_mylist_counter": 11
    },
    {
      "group": 26,
      "avg_view_counter": 838,
      "avg_mylist_counter": 19,
      "median_view_counter": 329,
      "median_mylist_counter": 15
    },
    {
      "group": 27,
      "avg_view_counter": 595,
      "avg_mylist_counter": 23,
      "median_view_counter": 326,
      "median_mylist_counter": 15
    },
    {
      "group": 28,
      "avg_view_counter": 468,
      "avg_mylist_counter": 16,
      "median_view_counter": 310,
      "median_mylist_counter": 12
    },
    {
      "group": 29,
      "avg_view_counter": 327,
      "avg_mylist_counter": 11,
      "median_view_counter": 223,
      "median_mylist_counter": 11
    },
    {
      "group": 30,
      "avg_view_counter": 300,
      "avg_mylist_counter": 21,
      "median_view_counter": 236,
      "median_mylist_counter": 23
    },
    {
      "group": 31,
      "avg_view_counter": 356,
      "avg_mylist_counter": 15,
      "median_view_counter": 271,
      "median_mylist_counter": 14
    },
    {
      "group": 32,
      "avg_view_counter": 388,
      "avg_mylist_counter": 13,
      "median_view_counter": 278,
      "median_mylist_counter": 12
    },
    {
      "group": 33,
      "avg_view_counter": 1360,
      "avg_mylist_counter": 29,
      "median_view_counter": 631,
      "median_mylist_counter": 17
    },
    {
      "group": 34,
      "avg_view_counter": 380,
      "avg_mylist_counter": 14,
      "median_view_counter": 239,
      "median_mylist_counter": 12
    },
    {
      "group": 35,
      "avg_view_counter": 333,
      "avg_mylist_counter": 16,
      "median_view_counter": 262,
      "median_mylist_counter": 13
    },
    {
      "group": 36,
      "avg_view_counter": 720,
      "avg_mylist_counter": 32,
      "median_view_counter": 537,
      "median_mylist_counter": 21
    },
    {
      "group": 37,
      "avg_view_counter": 355,
      "avg_mylist_counter": 19,
      "median_view_counter": 245,
      "median_mylist_counter": 16
    },
    {
      "group": 38,
      "avg_view_counter": 455,
      "avg_mylist_counter": 15,
      "median_view_counter": 244,
      "median_mylist_counter": 14
    },
    {
      "group": 39,
      "avg_view_counter": 593,
      "avg_mylist_counter": 26,
      "median_view_counter": 372,
      "median_mylist_counter": 20
    },
    {
      "group": 40,
      "avg_view_counter": 441,
      "avg_mylist_counter": 13,
      "median_view_counter": 287,
      "median_mylist_counter": 11
    },
    {
      "group": 41,
      "avg_view_counter": 536,
      "avg_mylist_counter": 17,
      "median_view_counter": 260,
      "median_mylist_counter": 12
    },
    {
      "group": 42,
      "avg_view_counter": 582,
      "avg_mylist_counter": 29,
      "median_view_counter": 310,
      "median_mylist_counter": 14
    },
    {
      "group": 43,
      "avg_view_counter": 484,
      "avg_mylist_counter": 18,
      "median_view_counter": 262,
      "median_mylist_counter": 18
    },
    {
      "group": 44,
      "avg_view_counter": 312,
      "avg_mylist_counter": 16,
      "median_view_counter": 296,
      "median_mylist_counter": 12
    },
    {
      "group": 45,
      "avg_view_counter": 649,
      "avg_mylist_counter": 19,
      "median_view_counter": 454,
      "median_mylist_counter": 16
    },
    {
      "group": 46,
      "avg_view_counter": 281,
      "avg_mylist_counter": 16,
      "median_view_counter": 287,
      "median_mylist_counter": 15
    },
    {
      "group": 47,
      "avg_view_counter": 930,
      "avg_mylist_counter": 32,
      "median_view_counter": 340,
      "median_mylist_counter": 18
    },
    {
      "group": 48,
      "avg_view_counter": 1269,
      "avg_mylist_counter": 16,
      "median_view_counter": 354,
      "median_mylist_counter": 14
    },
    {
      "group": 49,
      "avg_view_counter": 220,
      "avg_mylist_counter": 15,
      "median_view_counter": 224,
      "median_mylist_counter": 14
    },
    {
      "group": 50,
      "avg_view_counter": 416,
      "avg_mylist_counter": 18,
      "median_view_counter": 283,
      "median_mylist_counter": 12
    },
    {
      "group": 51,
      "avg_view_counter": 303,
      "avg_mylist_counter": 16,
      "median_view_counter": 278,
      "median_mylist_counter": 12
    },
    {
      "group": 52,
      "avg_view_counter": 540,
      "avg_mylist_counter": 20,
      "median_view_counter": 385,
      "median_mylist_counter": 12
    },
    {
      "group": 53,
      "avg_view_counter": 493,
      "avg_mylist_counter": 16,
      "median_view_counter": 290,
      "median_mylist_counter": 14
    },
    {
      "group": 54,
      "avg_view_counter": 406,
      "avg_mylist_counter": 16,
      "median_view_counter": 292,
      "median_mylist_counter": 14
    },
    {
      "group": 55,
      "avg_view_counter": 377,
      "avg_mylist_counter": 20,
      "median_view_counter": 295,
      "median_mylist_counter": 12
    },
    {
      "group": 56,
      "avg_view_counter": 320,
      "avg_mylist_counter": 17,
      "median_view_counter": 240,
      "median_mylist_counter": 18
    },
    {
      "group": 57,
      "avg_view_counter": 223,
      "avg_mylist_counter": 13,
      "median_view_counter": 226,
      "median_mylist_counter": 14
    },
    {
      "group": 58,
      "avg_view_counter": 369,
      "avg_mylist_counter": 15,
      "median_view_counter": 238,
      "median_mylist_counter": 14
    },
    {
      "group": 59,
      "avg_view_counter": 503,
      "avg_mylist_counter": 16,
      "median_view_counter": 274,
      "median_mylist_counter": 15
    },
    {
      "group": 60,
      "avg_view_counter": 566,
      "avg_mylist_counter": 19,
      "median_view_counter": 240,
      "median_mylist_counter": 15
    },
    {
      "group": 61,
      "avg_view_counter": 593,
      "avg_mylist_counter": 25,
      "median_view_counter": 362,
      "median_mylist_counter": 20
    },
    {
      "group": 62,
      "avg_view_counter": 596,
      "avg_mylist_counter": 23,
      "median_view_counter": 396,
      "median_mylist_counter": 21
    },
    {
      "group": 63,
      "avg_view_counter": 705,
      "avg_mylist_counter": 23,
      "median_view_counter": 793,
      "median_mylist_counter": 20
    },
    {
      "group": 64,
      "avg_view_counter": 554,
      "avg_mylist_counter": 25,
      "median_view_counter": 347,
      "median_mylist_counter": 25
    },
    {
      "group": 65,
      "avg_view_counter": 472,
      "avg_mylist_counter": 21,
      "median_view_counter": 445,
      "median_mylist_counter": 20
    },
    {
      "group": 66,
      "avg_view_counter": 280,
      "avg_mylist_counter": 13,
      "median_view_counter": 286,
      "median_mylist_counter": 10
    },
    {
      "group": 67,
      "avg_view_counter": 496,
      "avg_mylist_counter": 19,
      "median_view_counter": 336,
      "median_mylist_counter": 16
    },
    {
      "group": 68,
      "avg_view_counter": 636,
      "avg_mylist_counter": 33,
      "median_view_counter": 315,
      "median_mylist_counter": 23
    },
    {
      "group": 69,
      "avg_view_counter": 360,
      "avg_mylist_counter": 17,
      "median_view_counter": 273,
      "median_mylist_counter": 14
    },
    {
      "group": 70,
      "avg_view_counter": 325,
      "avg_mylist_counter": 15,
      "median_view_counter": 286,
      "median_mylist_counter": 12
    }
  ]
}