{
  "lastUpdated": "2026-04-28T19:30:13.399Z",
  "global": {
    "total_videos": 713,
    "avg_view_counter": 414,
    "median_view_counter": 238,
    "avg_mylist_counter": 16,
    "median_mylist_counter": 12
  },
  "stats": [
    {
      "group": 1,
      "avg_view_counter": 905,
      "avg_mylist_counter": 30,
      "median_view_counter": 692,
      "median_mylist_counter": 30
    },
    {
      "group": 2,
      "avg_view_counter": 566,
      "avg_mylist_counter": 21,
      "median_view_counter": 417,
      "median_mylist_counter": 20
    },
    {
      "group": 3,
      "avg_view_counter": 679,
      "avg_mylist_counter": 29,
      "median_view_counter": 579,
      "median_mylist_counter": 25
    },
    {
      "group": 4,
      "avg_view_counter": 285,
      "avg_mylist_counter": 13,
      "median_view_counter": 189,
      "median_mylist_counter": 10
    },
    {
      "group": 5,
      "avg_view_counter": 276,
      "avg_mylist_counter": 14,
      "median_view_counter": 237,
      "median_mylist_counter": 11
    },
    {
      "group": 6,
      "avg_view_counter": 382,
      "avg_mylist_counter": 13,
      "median_view_counter": 323,
      "median_mylist_counter": 10
    },
    {
      "group": 7,
      "avg_view_counter": 279,
      "avg_mylist_counter": 15,
      "median_view_counter": 211,
      "median_mylist_counter": 13
    },
    {
      "group": 8,
      "avg_view_counter": 584,
      "avg_mylist_counter": 29,
      "median_view_counter": 326,
      "median_mylist_counter": 16
    },
    {
      "group": 9,
      "avg_view_counter": 337,
      "avg_mylist_counter": 17,
      "median_view_counter": 219,
      "median_mylist_counter": 12
    },
    {
      "group": 10,
      "avg_view_counter": 365,
      "avg_mylist_counter": 15,
      "median_view_counter": 315,
      "median_mylist_counter": 11
    },
    {
      "group": 11,
      "avg_view_counter": 288,
      "avg_mylist_counter": 13,
      "median_view_counter": 235,
      "median_mylist_counter": 12
    },
    {
      "group": 12,
      "avg_view_counter": 374,
      "avg_mylist_counter": 12,
      "median_view_counter": 201,
      "median_mylist_counter": 10
    },
    {
      "group": 13,
      "avg_view_counter": 463,
      "avg_mylist_counter": 12,
      "median_view_counter": 233,
      "median_mylist_counter": 11
    },
    {
      "group": 14,
      "avg_view_counter": 969,
      "avg_mylist_counter": 36,
      "median_view_counter": 369,
      "median_mylist_counter": 22
    },
    {
      "group": 15,
      "avg_view_counter": 391,
      "avg_mylist_counter": 10,
      "median_view_counter": 193,
      "median_mylist_counter": 10
    },
    {
      "group": 16,
      "avg_view_counter": 402,
      "avg_mylist_counter": 20,
      "median_view_counter": 243,
      "median_mylist_counter": 14
    },
    {
      "group": 17,
      "avg_view_counter": 554,
      "avg_mylist_counter": 20,
      "median_view_counter": 215,
      "median_mylist_counter": 12
    },
    {
      "group": 18,
      "avg_view_counter": 358,
      "avg_mylist_counter": 11,
      "median_view_counter": 213,
      "median_mylist_counter": 10
    },
    {
      "group": 19,
      "avg_view_counter": 280,
      "avg_mylist_counter": 19,
      "median_view_counter": 227,
      "median_mylist_counter": 14
    },
    {
      "group": 20,
      "avg_view_counter": 216,
      "avg_mylist_counter": 14,
      "median_view_counter": 186,
      "median_mylist_counter": 10
    },
    {
      "group": 21,
      "avg_view_counter": 520,
      "avg_mylist_counter": 18,
      "median_view_counter": 310,
      "median_mylist_counter": 12
    },
    {
      "group": 22,
      "avg_view_counter": 554,
      "avg_mylist_counter": 21,
      "median_view_counter": 258,
      "median_mylist_counter": 12
    },
    {
      "group": 23,
      "avg_view_counter": 260,
      "avg_mylist_counter": 18,
      "median_view_counter": 237,
      "median_mylist_counter": 15
    },
    {
      "group": 24,
      "avg_view_counter": 482,
      "avg_mylist_counter": 16,
      "median_view_counter": 193,
      "median_mylist_counter": 13
    },
    {
      "group": 25,
      "avg_view_counter": 218,
      "avg_mylist_counter": 13,
      "median_view_counter": 192,
      "median_mylist_counter": 9
    },
    {
      "group": 26,
      "avg_view_counter": 566,
      "avg_mylist_counter": 17,
      "median_view_counter": 269,
      "median_mylist_counter": 14
    },
    {
      "group": 27,
      "avg_view_counter": 510,
      "avg_mylist_counter": 21,
      "median_view_counter": 259,
      "median_mylist_counter": 13
    },
    {
      "group": 28,
      "avg_view_counter": 356,
      "avg_mylist_counter": 13,
      "median_view_counter": 245,
      "median_mylist_counter": 11
    },
    {
      "group": 29,
      "avg_view_counter": 252,
      "avg_mylist_counter": 10,
      "median_view_counter": 176,
      "median_mylist_counter": 9
    },
    {
      "group": 30,
      "avg_view_counter": 238,
      "avg_mylist_counter": 18,
      "median_view_counter": 193,
      "median_mylist_counter": 20
    },
    {
      "group": 31,
      "avg_view_counter": 287,
      "avg_mylist_counter": 13,
      "median_view_counter": 193,
      "median_mylist_counter": 13
    },
    {
      "group": 32,
      "avg_view_counter": 327,
      "avg_mylist_counter": 12,
      "median_view_counter": 219,
      "median_mylist_counter": 11
    },
    {
      "group": 33,
      "avg_view_counter": 1168,
      "avg_mylist_counter": 25,
      "median_view_counter": 533,
      "median_mylist_counter": 14
    },
    {
      "group": 34,
      "avg_view_counter": 309,
      "avg_mylist_counter": 13,
      "median_view_counter": 193,
      "median_mylist_counter": 12
    },
    {
      "group": 35,
      "avg_view_counter": 255,
      "avg_mylist_counter": 14,
      "median_view_counter": 173,
      "median_mylist_counter": 10
    },
    {
      "group": 36,
      "avg_view_counter": 567,
      "avg_mylist_counter": 27,
      "median_view_counter": 420,
      "median_mylist_counter": 17
    },
    {
      "group": 37,
      "avg_view_counter": 267,
      "avg_mylist_counter": 15,
      "median_view_counter": 178,
      "median_mylist_counter": 11
    },
    {
      "group": 38,
      "avg_view_counter": 364,
      "avg_mylist_counter": 12,
      "median_view_counter": 175,
      "median_mylist_counter": 11
    },
    {
      "group": 39,
      "avg_view_counter": 441,
      "avg_mylist_counter": 22,
      "median_view_counter": 310,
      "median_mylist_counter": 17
    },
    {
      "group": 40,
      "avg_view_counter": 359,
      "avg_mylist_counter": 11,
      "median_view_counter": 246,
      "median_mylist_counter": 9
    },
    {
      "group": 41,
      "avg_view_counter": 444,
      "avg_mylist_counter": 16,
      "median_view_counter": 217,
      "median_mylist_counter": 11
    },
    {
      "group": 42,
      "avg_view_counter": 463,
      "avg_mylist_counter": 26,
      "median_view_counter": 249,
      "median_mylist_counter": 13
    },
    {
      "group": 43,
      "avg_view_counter": 404,
      "avg_mylist_counter": 17,
      "median_view_counter": 203,
      "median_mylist_counter": 16
    },
    {
      "group": 44,
      "avg_view_counter": 247,
      "avg_mylist_counter": 13,
      "median_view_counter": 231,
      "median_mylist_counter": 10
    },
    {
      "group": 45,
      "avg_view_counter": 495,
      "avg_mylist_counter": 15,
      "median_view_counter": 364,
      "median_mylist_counter": 14
    },
    {
      "group": 46,
      "avg_view_counter": 213,
      "avg_mylist_counter": 13,
      "median_view_counter": 214,
      "median_mylist_counter": 11
    },
    {
      "group": 47,
      "avg_view_counter": 770,
      "avg_mylist_counter": 27,
      "median_view_counter": 261,
      "median_mylist_counter": 12
    },
    {
      "group": 48,
      "avg_view_counter": 992,
      "avg_mylist_counter": 13,
      "median_view_counter": 281,
      "median_mylist_counter": 10
    },
    {
      "group": 49,
      "avg_view_counter": 174,
      "avg_mylist_counter": 13,
      "median_view_counter": 180,
      "median_mylist_counter": 13
    },
    {
      "group": 50,
      "avg_view_counter": 300,
      "avg_mylist_counter": 14,
      "median_view_counter": 216,
      "median_mylist_counter": 10
    },
    {
      "group": 51,
      "avg_view_counter": 241,
      "avg_mylist_counter": 14,
      "median_view_counter": 217,
      "median_mylist_counter": 11
    },
    {
      "group": 52,
      "avg_view_counter": 386,
      "avg_mylist_counter": 15,
      "median_view_counter": 280,
      "median_mylist_counter": 9
    },
    {
      "group": 53,
      "avg_view_counter": 372,
      "avg_mylist_counter": 13,
      "median_view_counter": 236,
      "median_mylist_counter": 12
    },
    {
      "group": 54,
      "avg_view_counter": 284,
      "avg_mylist_counter": 12,
      "median_view_counter": 210,
      "median_mylist_counter": 11
    },
    {
      "group": 55,
      "avg_view_counter": 302,
      "avg_mylist_counter": 15,
      "median_view_counter": 261,
      "median_mylist_counter": 10
    },
    {
      "group": 56,
      "avg_view_counter": 254,
      "avg_mylist_counter": 12,
      "median_view_counter": 170,
      "median_mylist_counter": 12
    },
    {
      "group": 57,
      "avg_view_counter": 178,
      "avg_mylist_counter": 9,
      "median_view_counter": 181,
      "median_mylist_counter": 10
    },
    {
      "group": 58,
      "avg_view_counter": 306,
      "avg_mylist_counter": 10,
      "median_view_counter": 181,
      "median_mylist_counter": 9
    },
    {
      "group": 59,
      "avg_view_counter": 320,
      "avg_mylist_counter": 11,
      "median_view_counter": 228,
      "median_mylist_counter": 10
    },
    {
      "group": 60,
      "avg_view_counter": 393,
      "avg_mylist_counter": 14,
      "median_view_counter": 189,
      "median_mylist_counter": 11
    },
    {
      "group": 61,
      "avg_view_counter": 493,
      "avg_mylist_counter": 18,
      "median_view_counter": 300,
      "median_mylist_counter": 14
    },
    {
      "group": 62,
      "avg_view_counter": 480,
      "avg_mylist_counter": 18,
      "median_view_counter": 292,
      "median_mylist_counter": 16
    },
    {
      "group": 63,
      "avg_view_counter": 553,
      "avg_mylist_counter": 18,
      "median_view_counter": 465,
      "median_mylist_counter": 15
    },
    {
      "group": 64,
      "avg_view_counter": 468,
      "avg_mylist_counter": 20,
      "median_view_counter": 284,
      "median_mylist_counter": 17
    },
    {
      "group": 65,
      "avg_view_counter": 363,
      "avg_mylist_counter": 17,
      "median_view_counter": 345,
      "median_mylist_counter": 15
    },
    {
      "group": 66,
      "avg_view_counter": 228,
      "avg_mylist_counter": 10,
      "median_view_counter": 226,
      "median_mylist_counter": 7
    },
    {
      "group": 67,
      "avg_view_counter": 406,
      "avg_mylist_counter": 15,
      "median_view_counter": 283,
      "median_mylist_counter": 13
    },
    {
      "group": 68,
      "avg_view_counter": 527,
      "avg_mylist_counter": 28,
      "median_view_counter": 269,
      "median_mylist_counter": 19
    },
    {
      "group": 69,
      "avg_view_counter": 298,
      "avg_mylist_counter": 13,
      "median_view_counter": 224,
      "median_mylist_counter": 10
    },
    {
      "group": 70,
      "avg_view_counter": 258,
      "avg_mylist_counter": 11,
      "median_view_counter": 247,
      "median_mylist_counter": 9
    }
  ]
}