{
  "lastUpdated": "2026-05-27T21:39:34.408Z",
  "global": {
    "total_videos": 350,
    "avg_view_counter": 1181,
    "median_view_counter": 799,
    "avg_mylist_counter": 42,
    "median_mylist_counter": 35
  },
  "stats": [
    {
      "group": 1,
      "avg_view_counter": 1333,
      "avg_mylist_counter": 44,
      "median_view_counter": 907,
      "median_mylist_counter": 35
    },
    {
      "group": 2,
      "avg_view_counter": 1017,
      "avg_mylist_counter": 41,
      "median_view_counter": 802,
      "median_mylist_counter": 40
    },
    {
      "group": 3,
      "avg_view_counter": 1357,
      "avg_mylist_counter": 43,
      "median_view_counter": 923,
      "median_mylist_counter": 40
    },
    {
      "group": 4,
      "avg_view_counter": 1291,
      "avg_mylist_counter": 47,
      "median_view_counter": 771,
      "median_mylist_counter": 41
    },
    {
      "group": 5,
      "avg_view_counter": 1026,
      "avg_mylist_counter": 49,
      "median_view_counter": 930,
      "median_mylist_counter": 51
    },
    {
      "group": 6,
      "avg_view_counter": 889,
      "avg_mylist_counter": 45,
      "median_view_counter": 761,
      "median_mylist_counter": 43
    },
    {
      "group": 7,
      "avg_view_counter": 1079,
      "avg_mylist_counter": 41,
      "median_view_counter": 925,
      "median_mylist_counter": 44
    },
    {
      "group": 8,
      "avg_view_counter": 1510,
      "avg_mylist_counter": 49,
      "median_view_counter": 730,
      "median_mylist_counter": 34
    },
    {
      "group": 9,
      "avg_view_counter": 1661,
      "avg_mylist_counter": 48,
      "median_view_counter": 776,
      "median_mylist_counter": 31
    },
    {
      "group": 10,
      "avg_view_counter": 1426,
      "avg_mylist_counter": 52,
      "median_view_counter": 872,
      "median_mylist_counter": 45
    },
    {
      "group": 11,
      "avg_view_counter": 1711,
      "avg_mylist_counter": 48,
      "median_view_counter": 1317,
      "median_mylist_counter": 46
    },
    {
      "group": 12,
      "avg_view_counter": 1313,
      "avg_mylist_counter": 43,
      "median_view_counter": 1034,
      "median_mylist_counter": 40
    },
    {
      "group": 13,
      "avg_view_counter": 887,
      "avg_mylist_counter": 36,
      "median_view_counter": 634,
      "median_mylist_counter": 33
    },
    {
      "group": 14,
      "avg_view_counter": 1124,
      "avg_mylist_counter": 40,
      "median_view_counter": 832,
      "median_mylist_counter": 37
    },
    {
      "group": 15,
      "avg_view_counter": 1063,
      "avg_mylist_counter": 47,
      "median_view_counter": 768,
      "median_mylist_counter": 38
    },
    {
      "group": 16,
      "avg_view_counter": 1587,
      "avg_mylist_counter": 52,
      "median_view_counter": 768,
      "median_mylist_counter": 37
    },
    {
      "group": 17,
      "avg_view_counter": 1319,
      "avg_mylist_counter": 41,
      "median_view_counter": 797,
      "median_mylist_counter": 36
    },
    {
      "group": 18,
      "avg_view_counter": 1299,
      "avg_mylist_counter": 47,
      "median_view_counter": 1314,
      "median_mylist_counter": 43
    },
    {
      "group": 19,
      "avg_view_counter": 1147,
      "avg_mylist_counter": 44,
      "median_view_counter": 800,
      "median_mylist_counter": 40
    },
    {
      "group": 20,
      "avg_view_counter": 785,
      "avg_mylist_counter": 32,
      "median_view_counter": 747,
      "median_mylist_counter": 26
    },
    {
      "group": 21,
      "avg_view_counter": 1106,
      "avg_mylist_counter": 44,
      "median_view_counter": 891,
      "median_mylist_counter": 31
    },
    {
      "group": 22,
      "avg_view_counter": 878,
      "avg_mylist_counter": 36,
      "median_view_counter": 692,
      "median_mylist_counter": 33
    },
    {
      "group": 23,
      "avg_view_counter": 1081,
      "avg_mylist_counter": 43,
      "median_view_counter": 921,
      "median_mylist_counter": 36
    },
    {
      "group": 24,
      "avg_view_counter": 1318,
      "avg_mylist_counter": 33,
      "median_view_counter": 666,
      "median_mylist_counter": 35
    },
    {
      "group": 25,
      "avg_view_counter": 1717,
      "avg_mylist_counter": 56,
      "median_view_counter": 659,
      "median_mylist_counter": 25
    },
    {
      "group": 26,
      "avg_view_counter": 674,
      "avg_mylist_counter": 31,
      "median_view_counter": 695,
      "median_mylist_counter": 30
    },
    {
      "group": 27,
      "avg_view_counter": 854,
      "avg_mylist_counter": 40,
      "median_view_counter": 611,
      "median_mylist_counter": 28
    },
    {
      "group": 28,
      "avg_view_counter": 1308,
      "avg_mylist_counter": 37,
      "median_view_counter": 1135,
      "median_mylist_counter": 35
    },
    {
      "group": 29,
      "avg_view_counter": 852,
      "avg_mylist_counter": 28,
      "median_view_counter": 776,
      "median_mylist_counter": 24
    },
    {
      "group": 30,
      "avg_view_counter": 849,
      "avg_mylist_counter": 29,
      "median_view_counter": 655,
      "median_mylist_counter": 29
    },
    {
      "group": 31,
      "avg_view_counter": 1201,
      "avg_mylist_counter": 45,
      "median_view_counter": 775,
      "median_mylist_counter": 43
    },
    {
      "group": 32,
      "avg_view_counter": 1004,
      "avg_mylist_counter": 37,
      "median_view_counter": 888,
      "median_mylist_counter": 34
    },
    {
      "group": 33,
      "avg_view_counter": 858,
      "avg_mylist_counter": 35,
      "median_view_counter": 803,
      "median_mylist_counter": 32
    },
    {
      "group": 34,
      "avg_view_counter": 1508,
      "avg_mylist_counter": 49,
      "median_view_counter": 1078,
      "median_mylist_counter": 37
    },
    {
      "group": 35,
      "avg_view_counter": 1295,
      "avg_mylist_counter": 48,
      "median_view_counter": 1027,
      "median_mylist_counter": 44
    }
  ]
}