{
  "lastUpdated": "2026-05-09T23:36:07.528Z",
  "global": {
    "total_videos": 713,
    "avg_view_counter": 685,
    "median_view_counter": 448,
    "avg_mylist_counter": 25,
    "median_mylist_counter": 19
  },
  "stats": [
    {
      "group": 1,
      "avg_view_counter": 1323,
      "avg_mylist_counter": 38,
      "median_view_counter": 980,
      "median_mylist_counter": 40
    },
    {
      "group": 2,
      "avg_view_counter": 832,
      "avg_mylist_counter": 30,
      "median_view_counter": 787,
      "median_mylist_counter": 31
    },
    {
      "group": 3,
      "avg_view_counter": 1004,
      "avg_mylist_counter": 38,
      "median_view_counter": 875,
      "median_mylist_counter": 33
    },
    {
      "group": 4,
      "avg_view_counter": 481,
      "avg_mylist_counter": 23,
      "median_view_counter": 343,
      "median_mylist_counter": 19
    },
    {
      "group": 5,
      "avg_view_counter": 451,
      "avg_mylist_counter": 20,
      "median_view_counter": 452,
      "median_mylist_counter": 18
    },
    {
      "group": 6,
      "avg_view_counter": 713,
      "avg_mylist_counter": 19,
      "median_view_counter": 535,
      "median_mylist_counter": 16
    },
    {
      "group": 7,
      "avg_view_counter": 505,
      "avg_mylist_counter": 24,
      "median_view_counter": 483,
      "median_mylist_counter": 21
    },
    {
      "group": 8,
      "avg_view_counter": 803,
      "avg_mylist_counter": 38,
      "median_view_counter": 538,
      "median_mylist_counter": 26
    },
    {
      "group": 9,
      "avg_view_counter": 574,
      "avg_mylist_counter": 25,
      "median_view_counter": 364,
      "median_mylist_counter": 18
    },
    {
      "group": 10,
      "avg_view_counter": 593,
      "avg_mylist_counter": 20,
      "median_view_counter": 484,
      "median_mylist_counter": 16
    },
    {
      "group": 11,
      "avg_view_counter": 561,
      "avg_mylist_counter": 21,
      "median_view_counter": 499,
      "median_mylist_counter": 19
    },
    {
      "group": 12,
      "avg_view_counter": 688,
      "avg_mylist_counter": 17,
      "median_view_counter": 382,
      "median_mylist_counter": 14
    },
    {
      "group": 13,
      "avg_view_counter": 780,
      "avg_mylist_counter": 22,
      "median_view_counter": 436,
      "median_mylist_counter": 20
    },
    {
      "group": 14,
      "avg_view_counter": 1360,
      "avg_mylist_counter": 50,
      "median_view_counter": 565,
      "median_mylist_counter": 39
    },
    {
      "group": 15,
      "avg_view_counter": 701,
      "avg_mylist_counter": 19,
      "median_view_counter": 394,
      "median_mylist_counter": 18
    },
    {
      "group": 16,
      "avg_view_counter": 665,
      "avg_mylist_counter": 26,
      "median_view_counter": 430,
      "median_mylist_counter": 20
    },
    {
      "group": 17,
      "avg_view_counter": 778,
      "avg_mylist_counter": 28,
      "median_view_counter": 399,
      "median_mylist_counter": 17
    },
    {
      "group": 18,
      "avg_view_counter": 660,
      "avg_mylist_counter": 18,
      "median_view_counter": 389,
      "median_mylist_counter": 17
    },
    {
      "group": 19,
      "avg_view_counter": 491,
      "avg_mylist_counter": 27,
      "median_view_counter": 422,
      "median_mylist_counter": 23
    },
    {
      "group": 20,
      "avg_view_counter": 428,
      "avg_mylist_counter": 26,
      "median_view_counter": 399,
      "median_mylist_counter": 27
    },
    {
      "group": 21,
      "avg_view_counter": 780,
      "avg_mylist_counter": 24,
      "median_view_counter": 552,
      "median_mylist_counter": 18
    },
    {
      "group": 22,
      "avg_view_counter": 864,
      "avg_mylist_counter": 28,
      "median_view_counter": 457,
      "median_mylist_counter": 22
    },
    {
      "group": 23,
      "avg_view_counter": 474,
      "avg_mylist_counter": 25,
      "median_view_counter": 426,
      "median_mylist_counter": 19
    },
    {
      "group": 24,
      "avg_view_counter": 744,
      "avg_mylist_counter": 26,
      "median_view_counter": 396,
      "median_mylist_counter": 21
    },
    {
      "group": 25,
      "avg_view_counter": 463,
      "avg_mylist_counter": 22,
      "median_view_counter": 389,
      "median_mylist_counter": 14
    },
    {
      "group": 26,
      "avg_view_counter": 1001,
      "avg_mylist_counter": 25,
      "median_view_counter": 490,
      "median_mylist_counter": 19
    },
    {
      "group": 27,
      "avg_view_counter": 813,
      "avg_mylist_counter": 31,
      "median_view_counter": 507,
      "median_mylist_counter": 24
    },
    {
      "group": 28,
      "avg_view_counter": 668,
      "avg_mylist_counter": 22,
      "median_view_counter": 444,
      "median_mylist_counter": 18
    },
    {
      "group": 29,
      "avg_view_counter": 442,
      "avg_mylist_counter": 15,
      "median_view_counter": 336,
      "median_mylist_counter": 15
    },
    {
      "group": 30,
      "avg_view_counter": 452,
      "avg_mylist_counter": 28,
      "median_view_counter": 384,
      "median_mylist_counter": 30
    },
    {
      "group": 31,
      "avg_view_counter": 484,
      "avg_mylist_counter": 20,
      "median_view_counter": 397,
      "median_mylist_counter": 18
    },
    {
      "group": 32,
      "avg_view_counter": 510,
      "avg_mylist_counter": 15,
      "median_view_counter": 407,
      "median_mylist_counter": 15
    },
    {
      "group": 33,
      "avg_view_counter": 1536,
      "avg_mylist_counter": 36,
      "median_view_counter": 828,
      "median_mylist_counter": 25
    },
    {
      "group": 34,
      "avg_view_counter": 534,
      "avg_mylist_counter": 22,
      "median_view_counter": 378,
      "median_mylist_counter": 20
    },
    {
      "group": 35,
      "avg_view_counter": 510,
      "avg_mylist_counter": 23,
      "median_view_counter": 425,
      "median_mylist_counter": 19
    },
    {
      "group": 36,
      "avg_view_counter": 956,
      "avg_mylist_counter": 39,
      "median_view_counter": 731,
      "median_mylist_counter": 28
    },
    {
      "group": 37,
      "avg_view_counter": 518,
      "avg_mylist_counter": 27,
      "median_view_counter": 387,
      "median_mylist_counter": 20
    },
    {
      "group": 38,
      "avg_view_counter": 601,
      "avg_mylist_counter": 19,
      "median_view_counter": 381,
      "median_mylist_counter": 18
    },
    {
      "group": 39,
      "avg_view_counter": 782,
      "avg_mylist_counter": 33,
      "median_view_counter": 521,
      "median_mylist_counter": 27
    },
    {
      "group": 40,
      "avg_view_counter": 594,
      "avg_mylist_counter": 18,
      "median_view_counter": 432,
      "median_mylist_counter": 15
    },
    {
      "group": 41,
      "avg_view_counter": 715,
      "avg_mylist_counter": 23,
      "median_view_counter": 427,
      "median_mylist_counter": 18
    },
    {
      "group": 42,
      "avg_view_counter": 757,
      "avg_mylist_counter": 35,
      "median_view_counter": 429,
      "median_mylist_counter": 17
    },
    {
      "group": 43,
      "avg_view_counter": 609,
      "avg_mylist_counter": 22,
      "median_view_counter": 406,
      "median_mylist_counter": 22
    },
    {
      "group": 44,
      "avg_view_counter": 451,
      "avg_mylist_counter": 22,
      "median_view_counter": 432,
      "median_mylist_counter": 16
    },
    {
      "group": 45,
      "avg_view_counter": 848,
      "avg_mylist_counter": 26,
      "median_view_counter": 673,
      "median_mylist_counter": 23
    },
    {
      "group": 46,
      "avg_view_counter": 448,
      "avg_mylist_counter": 21,
      "median_view_counter": 446,
      "median_mylist_counter": 20
    },
    {
      "group": 47,
      "avg_view_counter": 1173,
      "avg_mylist_counter": 42,
      "median_view_counter": 486,
      "median_mylist_counter": 29
    },
    {
      "group": 48,
      "avg_view_counter": 1423,
      "avg_mylist_counter": 20,
      "median_view_counter": 488,
      "median_mylist_counter": 21
    },
    {
      "group": 49,
      "avg_view_counter": 337,
      "avg_mylist_counter": 19,
      "median_view_counter": 334,
      "median_mylist_counter": 17
    },
    {
      "group": 50,
      "avg_view_counter": 553,
      "avg_mylist_counter": 23,
      "median_view_counter": 407,
      "median_mylist_counter": 15
    },
    {
      "group": 51,
      "avg_view_counter": 415,
      "avg_mylist_counter": 19,
      "median_view_counter": 403,
      "median_mylist_counter": 13
    },
    {
      "group": 52,
      "avg_view_counter": 712,
      "avg_mylist_counter": 23,
      "median_view_counter": 542,
      "median_mylist_counter": 15
    },
    {
      "group": 53,
      "avg_view_counter": 601,
      "avg_mylist_counter": 16,
      "median_view_counter": 391,
      "median_mylist_counter": 16
    },
    {
      "group": 54,
      "avg_view_counter": 586,
      "avg_mylist_counter": 23,
      "median_view_counter": 452,
      "median_mylist_counter": 24
    },
    {
      "group": 55,
      "avg_view_counter": 581,
      "avg_mylist_counter": 26,
      "median_view_counter": 435,
      "median_mylist_counter": 16
    },
    {
      "group": 56,
      "avg_view_counter": 454,
      "avg_mylist_counter": 22,
      "median_view_counter": 391,
      "median_mylist_counter": 22
    },
    {
      "group": 57,
      "avg_view_counter": 336,
      "avg_mylist_counter": 17,
      "median_view_counter": 323,
      "median_mylist_counter": 16
    },
    {
      "group": 58,
      "avg_view_counter": 508,
      "avg_mylist_counter": 18,
      "median_view_counter": 372,
      "median_mylist_counter": 15
    },
    {
      "group": 59,
      "avg_view_counter": 694,
      "avg_mylist_counter": 24,
      "median_view_counter": 436,
      "median_mylist_counter": 23
    },
    {
      "group": 60,
      "avg_view_counter": 748,
      "avg_mylist_counter": 24,
      "median_view_counter": 379,
      "median_mylist_counter": 18
    },
    {
      "group": 61,
      "avg_view_counter": 758,
      "avg_mylist_counter": 29,
      "median_view_counter": 545,
      "median_mylist_counter": 26
    },
    {
      "group": 62,
      "avg_view_counter": 830,
      "avg_mylist_counter": 28,
      "median_view_counter": 564,
      "median_mylist_counter": 25
    },
    {
      "group": 63,
      "avg_view_counter": 924,
      "avg_mylist_counter": 27,
      "median_view_counter": 1041,
      "median_mylist_counter": 26
    },
    {
      "group": 64,
      "avg_view_counter": 714,
      "avg_mylist_counter": 31,
      "median_view_counter": 546,
      "median_mylist_counter": 34
    },
    {
      "group": 65,
      "avg_view_counter": 660,
      "avg_mylist_counter": 26,
      "median_view_counter": 647,
      "median_mylist_counter": 24
    },
    {
      "group": 66,
      "avg_view_counter": 408,
      "avg_mylist_counter": 16,
      "median_view_counter": 397,
      "median_mylist_counter": 12
    },
    {
      "group": 67,
      "avg_view_counter": 638,
      "avg_mylist_counter": 24,
      "median_view_counter": 459,
      "median_mylist_counter": 19
    },
    {
      "group": 68,
      "avg_view_counter": 888,
      "avg_mylist_counter": 39,
      "median_view_counter": 450,
      "median_mylist_counter": 26
    },
    {
      "group": 69,
      "avg_view_counter": 513,
      "avg_mylist_counter": 21,
      "median_view_counter": 419,
      "median_mylist_counter": 17
    },
    {
      "group": 70,
      "avg_view_counter": 460,
      "avg_mylist_counter": 18,
      "median_view_counter": 396,
      "median_mylist_counter": 15
    }
  ]
}